odoo/addons/connector_importer_source_sftp/README.rst
odoo/addons/connector_importer_source_sftp/__init__.py
odoo/addons/connector_importer_source_sftp/__manifest__.py
odoo/addons/connector_importer_source_sftp/components/__init__.py
odoo/addons/connector_importer_source_sftp/components/event_listeners.py
odoo/addons/connector_importer_source_sftp/demo/import_source_demo.xml
odoo/addons/connector_importer_source_sftp/demo/storage_backend_demo.xml
odoo/addons/connector_importer_source_sftp/i18n/connector_importer_source_sftp.pot
odoo/addons/connector_importer_source_sftp/models/__init__.py
odoo/addons/connector_importer_source_sftp/models/source_csv_sftp.py
odoo/addons/connector_importer_source_sftp/models/source_mixin.py
odoo/addons/connector_importer_source_sftp/readme/CONTRIBUTORS.rst
odoo/addons/connector_importer_source_sftp/readme/DESCRIPTION.rst
odoo/addons/connector_importer_source_sftp/security/ir.model.access.csv
odoo/addons/connector_importer_source_sftp/static/description/icon.png
odoo/addons/connector_importer_source_sftp/static/description/index.html
odoo/addons/connector_importer_source_sftp/tests/__init__.py
odoo/addons/connector_importer_source_sftp/tests/common.py
odoo/addons/connector_importer_source_sftp/tests/test_csv_sftp_source.py
odoo/addons/connector_importer_source_sftp/tests/test_event_listener.py
odoo/addons/connector_importer_source_sftp/views/source_csv_sftp.xml
odoo13_addon_connector_importer_source_sftp-13.0.1.0.1.dev3.dist-info/METADATA
odoo13_addon_connector_importer_source_sftp-13.0.1.0.1.dev3.dist-info/WHEEL
odoo13_addon_connector_importer_source_sftp-13.0.1.0.1.dev3.dist-info/top_level.txt
odoo13_addon_connector_importer_source_sftp-13.0.1.0.1.dev3.dist-info/RECORD
