Metadata-Version: 2.1
Name: odoo13-addon-connector-importer-source-sftp
Version: 13.0.1.0.1.dev3
Summary: Add import source capable of loading files from SFTP.
Home-page: https://github.com/OCA/connector-interfaces
Author: Camptocamp,ACSONE,Odoo Community Association (OCA)
Author-email: support@odoo-community.org
License: AGPL-3
Platform: UNKNOWN
Classifier: Programming Language :: Python
Classifier: Framework :: Odoo
Classifier: Framework :: Odoo :: 13.0
Classifier: License :: OSI Approved :: GNU Affero General Public License v3
Requires-Python: >=3.5
Requires-Dist: odoo13-addon-component-event
Requires-Dist: odoo13-addon-connector-importer
Requires-Dist: odoo13-addon-storage-backend-sftp
Requires-Dist: odoo <13.1dev,>=13.0a
